[{
        "question": "Comment savoir si un projet est sous Maven?",
        "answer": "Il contient un fichier de configuration  pom.xml",
        "imgURI": "maven.png",
        "choices": [
            "Il contient un dossier serveur",
            "Il contient un fichier de configuration web.xml",
            "Il contient un fichier de configuration pom.xml",
            "Nous pouvons nous connecter à un serveur local avec un navigateur"
        ]
    },
    {
        "question": "Qu'est-ce que Eclipse Link?",
        "answer": "Un JPA",
        "imgURI": "eclipse_link.png",
        "choices": [
            "Un JPA",
            "Un gestionnaire de projet",
            "Un serveur local",
            "Un éditeur de code (IDE)"
        ]
    },
    {
        "question": "A quoi sert un JPA?",
        "answer": "Faire une liaison entre notre programme et notre base de données, (Faire la connection avec notre base de données)",
        "imgURI": "java.png",
        "choices": [
            "Gérer notre projet en ajoutant des outils pour les développeurs",
            "Faire une liaison entre notre programme et notre base de données",
            "Créer des endpoints pour tester depuis notre naviguateur",
            "Faire la connection avec notre base de données"
        ]
    },
    {
        "question": "Qu'est-ce que PostegresSQL?",
        "answer": "Un gestionnaire de base de données",
        "imgURI": "postgresql.jpg",
        "choices": [
            "Un JPA",
            "Un serveur local",
            "Un gestionnaire de base de données",
            "Un framework"
        ]
    },
    {
        "question": "Qu'est-ce que Tomcat?",
        "answer": "Un serveur local",
        "imgURI": "postgresql.jpg",
        "choices": [
            "Un gestionnaire de projet",
            "Un serveur local",
            "Un gestionnaire de base de données",
            "Un framework"
        ]
    },
    {
        "question": "Qu'est-ce que le design pattern \"Factory\"?",
        "answer": "Permet d'instancier différentes classes depuis une seul et même classe (en singleton)",
        "imgURI": "codes/factory.png",
        "choices": [

        ]
    },
    {
        "question": "Qu'est-ce que le design pattern \"Singleton\"?",
        "answer": "Permet d'avoir qu'une seul instance pour une classe qui ne peut avoir plusieurs instances (comme les classes DAO)",
        "imgURI": "codes/singleton.png",
        "choices": [

        ]
    },
    {
        "question": "Qu'est-ce que le design pattern \"Builder\"?",
        "answer": "Permet de construire un objet complexe étape par étape",
        "imgURI": "codes/builder.png",
        "choices": [

        ]
    },
    {
        "question": "Qu'est-ce que Maven?",
        "answer": "Un outil de gestion de dépendances",
        "imgURI": "maven.png",
        "choices": [

        ]
    },
    {
        "question": "Qu'est-ce que le fichier pom.xml?",
        "answer": "Un fichier de configuration de Maven",
        "imgURI": "maven.png",
        "choices": [

        ]
    },
    {
        "question": "Qu'est-ce qu'un entity manager?",
        "answer": "Un objet permettant de gérer les entités",
        "imgURI": "eclipse_link.png",
        "choices": [

        ]

    },
    {
        "question": "Quelles sont les trois techniques utilisées ici?",
        "answer": "Héritage, Abstraction, Polymorhisme",
        "imgURI": "codes/heritage.png",
        "choices": [
            "Encapsulation",
            "Héritage",
            "Abstraction",
            "Polymorphisme"
        ]
    },
    {
        "question": "Comment est appelé cette technique?",
        "answer": "Encapsulation",
        "imgURI": "codes/encapsulation.png",
        "choices": [

        ]
    },
    {
        "question": "Qu'est-ce que le verbe GET?",
        "answer": "Permet de récupérer des données",
        "imgURI": "http.jpg",
        "choices": [
            "Permet de récupérer des données",
            "Permet d'envoyer des données",
            "Permet de modifier des données",
            "Permet de supprimer des données"
        ]
    },
    {
        "question": "Qu'est-ce que le verbe POST?",
        "answer": "Permet d'envoyer des données",
        "imgURI": "http.jpg",
        "choices": [
            "Permet de récupérer des données",
            "Permet d'envoyer des données",
            "Permet de modifier des données",
            "Permet de supprimer des données"
        ]
    },
    {
        "question": "Qu'est-ce que le verbe PUT?",
        "answer": "Permet de modifier des données",
        "imgURI": "http.jpg",
        "choices": [
            "Permet de récupérer des données",
            "Permet d'envoyer des données",
            "Permet de modifier des données",
            "Permet de supprimer des données"
        ]
    },
    {
        "question": "Qu'est-ce que le verbe DELETE?",
        "answer": "Permet de supprimer des données",
        "imgURI": "http.jpg",
        "choices": [
            "Permet de récupérer des données",
            "Permet d'envoyer des données",
            "Permet de modifier des données",
            "Permet de supprimer des données"
        ]
    },
    {
        "question": "Qu'est-ce qu'une API Rest?",
        "answer": "Une API qui utilise les verbes HTTP",
        "imgURI": "http.jpg",
        "choices": [

        ]
    },
    {
        "question": "A quoi servent ces lignes de code?",
        "answer": "Permet de déclarer cette attribut comme clef primaire",
        "imgURI": "codes/annotGetId.png",
        "choices": [

        ]
    },
    {
        "question": "A quoi servent ces lignes de code?",
        "answer": "Permet de déclarer la classe comme une entité à lier avec la table Serie",
        "imgURI": "codes/annotEntity.png",
        "choices": [

        ]
    }
]